tronzap_sdk/__init__.py
tronzap_sdk/client.py
tronzap_sdk-1.0.7.dist-info/LICENSE
tronzap_sdk-1.0.7.dist-info/METADATA
tronzap_sdk-1.0.7.dist-info/WHEEL
tronzap_sdk-1.0.7.dist-info/top_level.txt
tronzap_sdk-1.0.7.dist-info/RECORD
