Metadata-Version: 2.1
Name: tronzap-sdk
Version: 1.0.7
Summary: Official Python SDK for the Tron Energy API by TronZap.com. Buy Tron energy for cheap USDT transfers on TronZap.com
Home-page: https://tronzap.com
Author: Tron Energy Market
Author-email: Tron Energy Market <support@tronzap.com>
License: MIT
Project-URL: Homepage, https://tronzap.com
Project-URL: Repository, https://github.com/tron-energy-market/tronzap-sdk-python
Project-URL: Documentation, https://docs.tronzap.com/
Project-URL: Issues, https://github.com/tron-energy-market/tronzap-sdk-python/issues
Project-URL: Buy Tron Energy, https://tronzap.com
Project-URL: Support, https://t.me/tronzap_bot
Keywords: TronZap,Tron,Trx,Tron API,Trx API,TRX energy,Tron energy,TRON energy api,buy trx energy,buy tron energy,trx energy market,tron energy market,usdt energy,tether energy,USDT,TRC20,TRC-20,cryptocurrency,blockchain,crypto transfers
Classifier: Development Status :: 5 - Production/Stable
Classifier: Intended Audience :: Developers
Classifier: License :: OSI Approved :: MIT License
Classifier: Programming Language :: Python :: 3
Requires-Python: >=3
License-File: LICENSE
